django_selenium_pdfmaker/__init__.py
django_selenium_pdfmaker/admin.py
django_selenium_pdfmaker/models.py
django_selenium_pdfmaker/modules.py
django_selenium_pdfmaker/settings.py
django_selenium_pdfmaker/tests.py
django_selenium_pdfmaker/__pycache__/__init__.cpython-310.pyc
django_selenium_pdfmaker/__pycache__/__init__.cpython-36.pyc
django_selenium_pdfmaker/__pycache__/__init__.cpython-39.pyc
django_selenium_pdfmaker/__pycache__/admin.cpython-310.pyc
django_selenium_pdfmaker/__pycache__/admin.cpython-36.pyc
django_selenium_pdfmaker/__pycache__/admin.cpython-39.pyc
django_selenium_pdfmaker/__pycache__/models.cpython-310.pyc
django_selenium_pdfmaker/__pycache__/models.cpython-36.pyc
django_selenium_pdfmaker/__pycache__/models.cpython-39.pyc
django_selenium_pdfmaker/__pycache__/modules.cpython-310.pyc
django_selenium_pdfmaker/__pycache__/modules.cpython-39.pyc
django_selenium_pdfmaker/__pycache__/settings.cpython-310.pyc
django_selenium_pdfmaker/__pycache__/tests.cpython-310.pyc
django_selenium_pdfmaker/__pycache__/tests.cpython-39.pyc
django_selenium_pdfmaker/management/__init__.py
django_selenium_pdfmaker/management/__pycache__/__init__.cpython-310.pyc
django_selenium_pdfmaker/management/commands/__init__.py
django_selenium_pdfmaker/management/commands/pdfmaker_install_chromedriver.py
django_selenium_pdfmaker/management/commands/__pycache__/__init__.cpython-310.pyc
django_selenium_pdfmaker/management/commands/__pycache__/pdfmaker_install_chromedriver.cpython-310.pyc
django_selenium_pdfmaker/migrations/0001_initial.py
django_selenium_pdfmaker/migrations/__init__.py
django_selenium_pdfmaker/migrations/__pycache__/0001_initial.cpython-310.pyc
django_selenium_pdfmaker/migrations/__pycache__/0001_initial.cpython-36.pyc
django_selenium_pdfmaker/migrations/__pycache__/0001_initial.cpython-39.pyc
django_selenium_pdfmaker/migrations/__pycache__/__init__.cpython-310.pyc
django_selenium_pdfmaker/migrations/__pycache__/__init__.cpython-36.pyc
django_selenium_pdfmaker-0.0.5.dist-info/LICENSE
django_selenium_pdfmaker-0.0.5.dist-info/METADATA
django_selenium_pdfmaker-0.0.5.dist-info/WHEEL
django_selenium_pdfmaker-0.0.5.dist-info/top_level.txt
django_selenium_pdfmaker-0.0.5.dist-info/RECORD
